{
  "_class": "symbolInstance",
  "do_objectID": "03694B75-D03C-4C43-B911-FC853F0D47A9",
  "exportOptions": {
    "_class": "exportOptions",
    "exportFormats": [
    ],
    "includedLayerIds": [
    ],
    "layerOptions": 0,
    "shouldTrim": false
  },
  "frame": {
    "_class": "rect",
    "constrainProportions": false,
    "height": 46,
    "width": 117,
    "x": 246,
    "y": 0
  },
  "horizontalSpacing": 0,
  "isFlippedHorizontal": false,
  "isFlippedVertical": false,
  "isLocked": true,
  "isVisible": true,
  "layerListExpandedType": 0,
  "masterInfluenceEdgeMaxXPadding": 0,
  "masterInfluenceEdgeMaxYPadding": 0,
  "masterInfluenceEdgeMinXPadding": 0,
  "masterInfluenceEdgeMinYPadding": 0,
  "name": "3",
  "nameIsFixed": true,
  "overrideValues": [
    {
      "_class": "overrideValue",
      "overrideName": "16D87242-F3D5-44B2-B176-0F08113D1A1F_stringValue",
      "value": "3"
    },
    {
      "_class": "overrideValue",
      "overrideName": "3BA55AD5-30C4-410A-AD4D-BA0E967E7338_stringValue",
      "value": "DEF"
    }
  ],
  "overrides": {
    "16D87242-F3D5-44B2-B176-0F08113D1A1F": "3",
    "3BA55AD5-30C4-410A-AD4D-BA0E967E7338": "DEF"
  },
  "resizingConstraint": 63,
  "resizingType": 0,
  "rotation": 0,
  "scale": 0,
  "shouldBreakMaskChain": false,
  "style": {
    "_class": "style",
    "endDecorationType": 0,
    "miterLimit": 10,
    "startDecorationType": 0
  },
  "symbolID": "7CE58910-383B-455B-B119-813A70B6621A",
  "verticalSpacing": 0
}